{
  "ticker": "005930.KS",
  "fetchedAt": "2026-05-20T15:51:11.129268+00:00",
  "period": "7d",
  "interval": "1h",
  "points": [
    {
      "datetime": "2026-05-12T00:00:00+00:00",
      "date": "2026-05-12",
      "open": 290000.0,
      "high": 291500.0,
      "low": 284500.0,
      "close": 286500.0,
      "volume": 0
    },
    {
      "datetime": "2026-05-12T01:00:00+00:00",
      "date": "2026-05-12",
      "open": 286500.0,
      "high": 287500.0,
      "low": 266000.0,
      "close": 272500.0,
      "volume": 11574847
    },
    {
      "datetime": "2026-05-12T02:00:00+00:00",
      "date": "2026-05-12",
      "open": 272500.0,
      "high": 282500.0,
      "low": 271000.0,
      "close": 282500.0,
      "volume": 4939104
    },
    {
      "datetime": "2026-05-12T03:00:00+00:00",
      "date": "2026-05-12",
      "open": 282500.0,
      "high": 283000.0,
      "low": 276500.0,
      "close": 276500.0,
      "volume": 2413834
    },
    {
      "datetime": "2026-05-12T04:00:00+00:00",
      "date": "2026-05-12",
      "open": 276750.0,
      "high": 278000.0,
      "low": 272000.0,
      "close": 272750.0,
      "volume": 3647294
    },
    {
      "datetime": "2026-05-12T05:00:00+00:00",
      "date": "2026-05-12",
      "open": 272750.0,
      "high": 279000.0,
      "low": 271500.0,
      "close": 278000.0,
      "volume": 4594241
    },
    {
      "datetime": "2026-05-13T00:00:00+00:00",
      "date": "2026-05-13",
      "open": 264000.0,
      "high": 269500.0,
      "low": 262000.0,
      "close": 269000.0,
      "volume": 10727283
    },
    {
      "datetime": "2026-05-13T01:00:00+00:00",
      "date": "2026-05-13",
      "open": 269250.0,
      "high": 282000.0,
      "low": 268500.0,
      "close": 278750.0,
      "volume": 7180524
    },
    {
      "datetime": "2026-05-13T02:00:00+00:00",
      "date": "2026-05-13",
      "open": 278750.0,
      "high": 281000.0,
      "low": 276000.0,
      "close": 278000.0,
      "volume": 2955802
    },
    {
      "datetime": "2026-05-13T03:00:00+00:00",
      "date": "2026-05-13",
      "open": 278000.0,
      "high": 282000.0,
      "low": 277000.0,
      "close": 281500.0,
      "volume": 2369756
    },
    {
      "datetime": "2026-05-13T04:00:00+00:00",
      "date": "2026-05-13",
      "open": 281750.0,
      "high": 285000.0,
      "low": 281000.0,
      "close": 281750.0,
      "volume": 4555839
    },
    {
      "datetime": "2026-05-13T05:00:00+00:00",
      "date": "2026-05-13",
      "open": 281500.0,
      "high": 285500.0,
      "low": 279500.0,
      "close": 284750.0,
      "volume": 4175579
    },
    {
      "datetime": "2026-05-14T00:00:00+00:00",
      "date": "2026-05-14",
      "open": 282000.0,
      "high": 299500.0,
      "low": 282000.0,
      "close": 299500.0,
      "volume": 13018332
    },
    {
      "datetime": "2026-05-14T01:00:00+00:00",
      "date": "2026-05-14",
      "open": 299500.0,
      "high": 299500.0,
      "low": 292500.0,
      "close": 292500.0,
      "volume": 5381678
    },
    {
      "datetime": "2026-05-14T02:00:00+00:00",
      "date": "2026-05-14",
      "open": 292500.0,
      "high": 295000.0,
      "low": 288500.0,
      "close": 289000.0,
      "volume": 4290525
    },
    {
      "datetime": "2026-05-14T03:00:00+00:00",
      "date": "2026-05-14",
      "open": 289250.0,
      "high": 293500.0,
      "low": 288500.0,
      "close": 290000.0,
      "volume": 2701986
    },
    {
      "datetime": "2026-05-14T04:00:00+00:00",
      "date": "2026-05-14",
      "open": 290500.0,
      "high": 295000.0,
      "low": 289500.0,
      "close": 292500.0,
      "volume": 2911198
    },
    {
      "datetime": "2026-05-14T05:00:00+00:00",
      "date": "2026-05-14",
      "open": 293000.0,
      "high": 294500.0,
      "low": 290000.0,
      "close": 294000.0,
      "volume": 3633101
    },
    {
      "datetime": "2026-05-15T00:00:00+00:00",
      "date": "2026-05-15",
      "open": 291000.0,
      "high": 296500.0,
      "low": 290000.0,
      "close": 292750.0,
      "volume": 6043979
    },
    {
      "datetime": "2026-05-15T01:00:00+00:00",
      "date": "2026-05-15",
      "open": 292750.0,
      "high": 293500.0,
      "low": 284000.0,
      "close": 284500.0,
      "volume": 4996378
    },
    {
      "datetime": "2026-05-15T02:00:00+00:00",
      "date": "2026-05-15",
      "open": 284750.0,
      "high": 285500.0,
      "low": 278500.0,
      "close": 281750.0,
      "volume": 6148397
    },
    {
      "datetime": "2026-05-15T03:00:00+00:00",
      "date": "2026-05-15",
      "open": 281750.0,
      "high": 282500.0,
      "low": 278500.0,
      "close": 280250.0,
      "volume": 3314480
    },
    {
      "datetime": "2026-05-15T04:00:00+00:00",
      "date": "2026-05-15",
      "open": 280250.0,
      "high": 280250.0,
      "low": 273500.0,
      "close": 274250.0,
      "volume": 4987947
    },
    {
      "datetime": "2026-05-15T05:00:00+00:00",
      "date": "2026-05-15",
      "open": 274250.0,
      "high": 277000.0,
      "low": 267000.0,
      "close": 268000.0,
      "volume": 6627191
    },
    {
      "datetime": "2026-05-18T00:00:00+00:00",
      "date": "2026-05-18",
      "open": 269500.0,
      "high": 278500.0,
      "low": 262000.0,
      "close": 278500.0,
      "volume": 0
    },
    {
      "datetime": "2026-05-18T01:00:00+00:00",
      "date": "2026-05-18",
      "open": 278500.0,
      "high": 285000.0,
      "low": 272500.0,
      "close": 282000.0,
      "volume": 6937036
    },
    {
      "datetime": "2026-05-18T02:00:00+00:00",
      "date": "2026-05-18",
      "open": 282250.0,
      "high": 288500.0,
      "low": 280000.0,
      "close": 283000.0,
      "volume": 5060173
    },
    {
      "datetime": "2026-05-18T03:00:00+00:00",
      "date": "2026-05-18",
      "open": 283000.0,
      "high": 285000.0,
      "low": 279750.0,
      "close": 283500.0,
      "volume": 2653518
    },
    {
      "datetime": "2026-05-18T04:00:00+00:00",
      "date": "2026-05-18",
      "open": 284000.0,
      "high": 285500.0,
      "low": 280500.0,
      "close": 282000.0,
      "volume": 2305369
    },
    {
      "datetime": "2026-05-18T05:00:00+00:00",
      "date": "2026-05-18",
      "open": 282000.0,
      "high": 285000.0,
      "low": 277500.0,
      "close": 283000.0,
      "volume": 3176665
    },
    {
      "datetime": "2026-05-19T00:00:00+00:00",
      "date": "2026-05-19",
      "open": 274000.0,
      "high": 277000.0,
      "low": 271000.0,
      "close": 272000.0,
      "volume": 6761417
    },
    {
      "datetime": "2026-05-19T01:00:00+00:00",
      "date": "2026-05-19",
      "open": 272000.0,
      "high": 274000.0,
      "low": 268500.0,
      "close": 268500.0,
      "volume": 4638859
    },
    {
      "datetime": "2026-05-19T02:00:00+00:00",
      "date": "2026-05-19",
      "open": 269000.0,
      "high": 272500.0,
      "low": 266000.0,
      "close": 271750.0,
      "volume": 4035762
    },
    {
      "datetime": "2026-05-19T03:00:00+00:00",
      "date": "2026-05-19",
      "open": 272000.0,
      "high": 278500.0,
      "low": 269500.0,
      "close": 276500.0,
      "volume": 3124044
    },
    {
      "datetime": "2026-05-19T04:00:00+00:00",
      "date": "2026-05-19",
      "open": 276500.0,
      "high": 276500.0,
      "low": 271000.0,
      "close": 274750.0,
      "volume": 2520325
    },
    {
      "datetime": "2026-05-19T05:00:00+00:00",
      "date": "2026-05-19",
      "open": 274500.0,
      "high": 281500.0,
      "low": 273000.0,
      "close": 279750.0,
      "volume": 4364880
    },
    {
      "datetime": "2026-05-20T00:00:00+00:00",
      "date": "2026-05-20",
      "open": 278000.0,
      "high": 281000.0,
      "low": 271500.0,
      "close": 274500.0,
      "volume": 7555470
    },
    {
      "datetime": "2026-05-20T01:00:00+00:00",
      "date": "2026-05-20",
      "open": 274000.0,
      "high": 279000.0,
      "low": 272500.0,
      "close": 279000.0,
      "volume": 3607878
    },
    {
      "datetime": "2026-05-20T02:00:00+00:00",
      "date": "2026-05-20",
      "open": 279000.0,
      "high": 282500.0,
      "low": 263500.0,
      "close": 268000.0,
      "volume": 9026568
    },
    {
      "datetime": "2026-05-20T03:00:00+00:00",
      "date": "2026-05-20",
      "open": 268000.0,
      "high": 270000.0,
      "low": 265000.0,
      "close": 269000.0,
      "volume": 3187676
    },
    {
      "datetime": "2026-05-20T04:00:00+00:00",
      "date": "2026-05-20",
      "open": 268500.0,
      "high": 275000.0,
      "low": 268500.0,
      "close": 269500.0,
      "volume": 3587720
    },
    {
      "datetime": "2026-05-20T05:00:00+00:00",
      "date": "2026-05-20",
      "open": 270000.0,
      "high": 274500.0,
      "low": 269000.0,
      "close": 273500.0,
      "volume": 3189160
    }
  ]
}